homecloud/__init__.py
homecloud/client.py
homecloud/client_settings.toml
homecloud/client_subclass.py
homecloud/get_routes.py
homecloud/homecloud_config.toml
homecloud/homecloud_generator.py
homecloud/homecloud_logging.py
homecloud/homecloud_utils.py
homecloud/module_to_api.py
homecloud/post_routes.py
homecloud/request_models.py
homecloud/router_template.py
homecloud/server.py
homecloud-0.3.4.dist-info/METADATA
homecloud-0.3.4.dist-info/WHEEL
homecloud-0.3.4.dist-info/entry_points.txt
homecloud-0.3.4.dist-info/licenses/LICENSE.txt
homecloud-0.3.4.dist-info/RECORD
