Metadata-Version: 2.1
Name: homecloud
Version: 0.3.4
Summary: A command line tool for generating the template files needed to integrate fastapi, uvicorn, and a requests based client into a Python project.
Project-URL: Homepage, https://github.com/matt-manes/homecloud
Project-URL: Documentation, https://github.com/matt-manes/homecloud/tree/main/docs
Project-URL: Source code, https://github.com/matt-manes/homecloud/tree/main/src/homecloud
Author-email: Matt Manes <mattmanes@pm.me>
License-File: LICENSE.txt
Keywords: api,client,fastapi,network,server
Classifier: License :: OSI Approved :: MIT License
Classifier: Operating System :: OS Independent
Classifier: Programming Language :: Python :: 3
Requires-Python: >=3.10
Requires-Dist: black
Requires-Dist: dummy-client
Requires-Dist: fastapi
Requires-Dist: lanutils
Requires-Dist: pathier
Requires-Dist: pydantic
Requires-Dist: requests
Requires-Dist: tomlkit
